anrg_saga-2.0.2.dist-info/licenses/LICENSE
saga/__init__.py
saga/stochastic.py
saga/pisa/__init__.py
saga/pisa/changes.py
saga/pisa/simulated_annealing.py
saga/schedulers/__init__.py
saga/schedulers/bil.py
saga/schedulers/brute_force.py
saga/schedulers/cpop.py
saga/schedulers/dps.py
saga/schedulers/duplex.py
saga/schedulers/etf.py
saga/schedulers/fastest_node.py
saga/schedulers/fcp.py
saga/schedulers/flb.py
saga/schedulers/gdl.py
saga/schedulers/hbmct.py
saga/schedulers/heft.py
saga/schedulers/hybrid.py
saga/schedulers/maxmin.py
saga/schedulers/mct.py
saga/schedulers/met.py
saga/schedulers/minmin.py
saga/schedulers/msbc.py
saga/schedulers/mst.py
saga/schedulers/olb.py
saga/schedulers/smt.py
saga/schedulers/sufferage.py
saga/schedulers/wba.py
saga/schedulers/data/__init__.py
saga/schedulers/data/random.py
saga/schedulers/data/riotbench.py
saga/schedulers/data/wfcommons.py
saga/schedulers/parametric/__init__.py
saga/schedulers/parametric/components.py
saga/schedulers/stochastic/__init__.py
saga/schedulers/stochastic/determinizer.py
saga/schedulers/stochastic/mean_heft.py
saga/schedulers/stochastic/sheft.py
saga/schedulers/stochastic/data/__init__.py
saga/schedulers/stochastic/data/wfcommons.py
saga/utils/__init__.py
saga/utils/draw.py
saga/utils/random_graphs.py
saga/utils/random_variable.py
anrg_saga-2.0.2.dist-info/METADATA
anrg_saga-2.0.2.dist-info/WHEEL
anrg_saga-2.0.2.dist-info/top_level.txt
anrg_saga-2.0.2.dist-info/RECORD
