Metadata-Version: 2.4
Name: anrg-saga
Version: 2.0.2
Summary: Scheduling Algorithms Gathered - collection of task graph scheduling algorithms
Author-email: ANRG USC <anrg@usc.edu>
License: MIT
Project-URL: Repository, https://github.com/ANRGUSC/saga
Project-URL: Issues, https://github.com/ANRGUSC/saga/issues
Requires-Python: >=3.11
License-File: LICENSE
Requires-Dist: networkx
Requires-Dist: numpy
Requires-Dist: pandas
Requires-Dist: scipy
Requires-Dist: matplotlib
Requires-Dist: pydantic>=2.0
Requires-Dist: gitpython
Requires-Dist: pytest>=7.0.0
Requires-Dist: pytest-timeout>=2.1.0
Requires-Dist: mypy>=0.991
Requires-Dist: tqdm
Requires-Dist: filelock
Requires-Dist: pysmt
Requires-Dist: z3-solver
Requires-Dist: pygraphviz
Requires-Dist: wfcommons; sys_platform != "win32"
Dynamic: license-file
